<Gesture Name="delete" NumPts="49" Date="Monday, June 17, 2024" TimeOfDay="08:07:44 PM"><Point X="137" Y="430" T="1718647662.9841425" /><Point X="144" Y="419" T="1718647663.0666773" /><Point X="154" Y="405" T="1718647663.0836654" /><Point X="160" Y="397" T="1718647663.0869644" /><Point X="165" Y="389" T="1718647663.099334" /><Point X="171" Y="380" T="1718647663.100964" /><Point X="189" Y="351" T="1718647663.1308968" /><Point X="197" Y="337" T="1718647663.149596" /><Point X="208" Y="317" T="1718647663.1668513" /><Point X="214" Y="307" T="1718647663.1831458" /><Point X="221" Y="296" T="1718647663.1993573" /><Point X="224" Y="290" T="1718647663.2003648" /><Point X="231" Y="279" T="1718647663.216049" /><Point X="243" Y="258" T="1718647663.2489107" /><Point X="260" Y="230" T="1718647663.2816958" /><Point X="271" Y="209" T="1718647663.300443" /><Point X="285" Y="182" T="1718647663.3322072" /><Point X="302" Y="147" T="1718647663.3644495" /><Point X="317" Y="119" T="1718647663.4005399" /><Point X="325" Y="103" T="1718647663.450337" /><Point X="328" Y="98" T="1718647663.5008678" /><Point X="328" Y="96" T="1718647663.5495734" /><Point X="324" Y="96" T="1718647663.5835166" /><Point X="308" Y="98" T="1718647663.6160984" /><Point X="269" Y="98" T="1718647663.6659808" /><Point X="239" Y="99" T="1718647663.7005947" /><Point X="216" Y="100" T="1718647663.7326758" /><Point X="188" Y="100" T="1718647663.7659538" /><Point X="159" Y="100" T="1718647663.7988405" /><Point X="135" Y="102" T="1718647663.8327181" /><Point X="113" Y="104" T="1718647663.8665724" /><Point X="75" Y="106" T="1718647663.9174767" /><Point X="54" Y="106" T="1718647663.9665005" /><Point X="41" Y="106" T="1718647664.0164297" /><Point X="37" Y="108" T="1718647664.0658116" /><Point X="48" Y="125" T="1718647664.1167037" /><Point X="107" Y="201" T="1718647664.1841493" /><Point X="156" Y="259" T="1718647664.2402103" /><Point X="179" Y="289" T="1718647664.285069" /><Point X="184" Y="295" T="1718647664.2861087" /><Point X="202" Y="320" T="1718647664.3200457" /><Point X="237" Y="359" T="1718647664.3642783" /><Point X="260" Y="379" T="1718647664.400924" /><Point X="278" Y="396" T="1718647664.4369984" /><Point X="294" Y="408" T="1718647664.4734423" /><Point X="310" Y="420" T="1718647664.512134" /><Point X="317" Y="425" T="1718647664.5555286" /><Point X="320" Y="428" T="1718647664.5960875" /><Point X="322" Y="428" T="1718647664.639096" /></Gesture>