<Gesture Name="left-square-bracket" NumPts="43" Date="Monday, June 17, 2024" TimeOfDay="08:05:09 PM"><Point X="325" Y="430" T="1718647507.3072293" /><Point X="316" Y="430" T="1718647507.4354212" /><Point X="307" Y="430" T="1718647507.440448" /><Point X="277" Y="430" T="1718647507.469745" /><Point X="259" Y="430" T="1718647507.4865735" /><Point X="243" Y="431" T="1718647507.5019073" /><Point X="217" Y="432" T="1718647507.5186565" /><Point X="202" Y="432" T="1718647507.5360458" /><Point X="189" Y="432" T="1718647507.5530849" /><Point X="184" Y="432" T="1718647507.5530849" /><Point X="171" Y="431" T="1718647507.5689654" /><Point X="156" Y="430" T="1718647507.5863464" /><Point X="141" Y="430" T="1718647507.6023414" /><Point X="134" Y="429" T="1718647507.6033509" /><Point X="117" Y="429" T="1718647507.634243" /><Point X="109" Y="429" T="1718647507.6684163" /><Point X="106" Y="429" T="1718647507.700684" /><Point X="106" Y="428" T="1718647507.8678982" /><Point X="108" Y="419" T="1718647507.9020658" /><Point X="112" Y="402" T="1718647507.9353256" /><Point X="115" Y="383" T="1718647507.9684217" /><Point X="116" Y="352" T="1718647508.0016649" /><Point X="116" Y="330" T="1718647508.0353785" /><Point X="116" Y="309" T="1718647508.0684323" /><Point X="116" Y="280" T="1718647508.1018956" /><Point X="115" Y="229" T="1718647508.1347787" /><Point X="111" Y="163" T="1718647508.1687145" /><Point X="106" Y="119" T="1718647508.201939" /><Point X="105" Y="100" T="1718647508.2348077" /><Point X="105" Y="85" T="1718647508.268719" /><Point X="105" Y="69" T="1718647508.3183424" /><Point X="105" Y="63" T="1718647508.3517609" /><Point X="105" Y="59" T="1718647508.4017444" /><Point X="105" Y="58" T="1718647508.4520586" /><Point X="138" Y="63" T="1718647508.5514815" /><Point X="181" Y="69" T="1718647508.6018128" /><Point X="216" Y="71" T="1718647508.651467" /><Point X="242" Y="71" T="1718647508.7009025" /><Point X="263" Y="72" T="1718647508.7384162" /><Point X="277" Y="72" T="1718647508.7775297" /><Point X="292" Y="73" T="1718647508.815456" /><Point X="301" Y="75" T="1718647508.8554468" /><Point X="307" Y="76" T="1718647508.8949723" /></Gesture>