<Gesture Name="star" NumPts="84" Date="Monday, June 17, 2024" TimeOfDay="08:10:13 PM"><Point X="110" Y="140" T="1718647809.0985062" /><Point X="111" Y="143" T="1718647809.2299905" /><Point X="114" Y="152" T="1718647809.2467897" /><Point X="115" Y="157" T="1718647809.24779" /><Point X="119" Y="170" T="1718647809.2634587" /><Point X="125" Y="181" T="1718647809.2803085" /><Point X="137" Y="207" T="1718647809.3121297" /><Point X="143" Y="216" T="1718647809.3301206" /><Point X="150" Y="228" T="1718647809.3467903" /><Point X="155" Y="237" T="1718647809.3634555" /><Point X="159" Y="244" T="1718647809.3791096" /><Point X="164" Y="255" T="1718647809.3977692" /><Point X="167" Y="261" T="1718647809.4136958" /><Point X="175" Y="280" T="1718647809.4471807" /><Point X="182" Y="295" T="1718647809.478613" /><Point X="191" Y="316" T="1718647809.5130327" /><Point X="199" Y="337" T="1718647809.5467503" /><Point X="208" Y="355" T="1718647809.579994" /><Point X="214" Y="369" T="1718647809.6130378" /><Point X="221" Y="386" T="1718647809.6464093" /><Point X="227" Y="399" T="1718647809.6797721" /><Point X="232" Y="411" T="1718647809.730057" /><Point X="234" Y="415" T="1718647809.7624202" /><Point X="235" Y="417" T="1718647809.7966323" /><Point X="236" Y="418" T="1718647809.8299363" /><Point X="237" Y="416" T="1718647809.9301105" /><Point X="239" Y="409" T="1718647809.963672" /><Point X="245" Y="386" T="1718647809.996436" /><Point X="249" Y="371" T="1718647810.030091" /><Point X="250" Y="359" T="1718647810.0624402" /><Point X="253" Y="342" T="1718647810.0959997" /><Point X="257" Y="321" T="1718647810.1294768" /><Point X="260" Y="303" T="1718647810.1622963" /><Point X="264" Y="278" T="1718647810.1954308" /><Point X="269" Y="253" T="1718647810.2446413" /><Point X="271" Y="235" T="1718647810.281655" /><Point X="275" Y="219" T="1718647810.3156602" /><Point X="278" Y="204" T="1718647810.3519425" /><Point X="283" Y="182" T="1718647810.4003992" /><Point X="286" Y="169" T="1718647810.4368036" /><Point X="287" Y="155" T="1718647810.4736571" /><Point X="289" Y="145" T="1718647810.5121377" /><Point X="291" Y="139" T="1718647810.550819" /><Point X="291" Y="138" T="1718647810.550819" /><Point X="291" Y="137" T="1718647810.5898879" /><Point X="286" Y="140" T="1718647810.6723373" /><Point X="270" Y="154" T="1718647810.714964" /><Point X="247" Y="174" T="1718647810.7593987" /><Point X="220" Y="197" T="1718647810.8026786" /><Point X="200" Y="214" T="1718647810.8472564" /><Point X="176" Y="237" T="1718647810.9049523" /><Point X="156" Y="256" T="1718647810.9543293" /><Point X="137" Y="277" T="1718647811.003175" /><Point X="120" Y="293" T="1718647811.0513873" /><Point X="108" Y="306" T="1718647811.0971625" /><Point X="92" Y="320" T="1718647811.144585" /><Point X="76" Y="335" T="1718647811.1940727" /><Point X="66" Y="348" T="1718647811.246166" /><Point X="63" Y="352" T="1718647811.297926" /><Point X="74" Y="353" T="1718647811.358751" /><Point X="120" Y="349" T="1718647811.4148412" /><Point X="161" Y="346" T="1718647811.4716814" /><Point X="188" Y="343" T="1718647811.5256088" /><Point X="192" Y="342" T="1718647811.5256088" /><Point X="218" Y="338" T="1718647811.5820544" /><Point X="246" Y="334" T="1718647811.6407952" /><Point X="276" Y="333" T="1718647811.699634" /><Point X="301" Y="332" T="1718647811.758383" /><Point X="332" Y="327" T="1718647811.8281965" /><Point X="352" Y="326" T="1718647811.8898928" /><Point X="368" Y="326" T="1718647811.9536304" /><Point X="377" Y="326" T="1718647812.0203724" /><Point X="379" Y="324" T="1718647812.0846355" /><Point X="336" Y="296" T="1718647812.150631" /><Point X="303" Y="274" T="1718647812.2140532" /><Point X="268" Y="251" T="1718647812.2905672" /><Point X="244" Y="238" T="1718647812.357089" /><Point X="207" Y="216" T="1718647812.4240184" /><Point X="178" Y="195" T="1718647812.4904027" /><Point X="152" Y="176" T="1718647812.561389" /><Point X="132" Y="157" T="1718647812.6332266" /><Point X="112" Y="138" T="1718647812.7134807" /><Point X="105" Y="131" T="1718647812.7851167" /><Point X="105" Y="130" T="1718647812.8563685" /></Gesture>